sgUPFCMed/__init__.py
sgUPFCMed/sgUPFCMed.py
sgupfcmed-0.0.1.dist-info/licenses/LICENSE
test/__init__.py
test/test_sgUPFCMed.py
venv/Lib/site-packages/build/__init__.py
venv/Lib/site-packages/build/__main__.py
venv/Lib/site-packages/build/_builder.py
venv/Lib/site-packages/build/_ctx.py
venv/Lib/site-packages/build/_exceptions.py
venv/Lib/site-packages/build/_types.py
venv/Lib/site-packages/build/_util.py
venv/Lib/site-packages/build/env.py
venv/Lib/site-packages/build/py.typed
venv/Lib/site-packages/build/util.py
venv/Lib/site-packages/build/_compat/__init__.py
venv/Lib/site-packages/build/_compat/importlib.py
venv/Lib/site-packages/build/_compat/tarfile.py
venv/Lib/site-packages/build/_compat/tomllib.py
venv/Lib/site-packages/certifi/__init__.py
venv/Lib/site-packages/certifi/__main__.py
venv/Lib/site-packages/certifi/core.py
venv/Lib/site-packages/certifi/py.typed
venv/Lib/site-packages/charset_normalizer/__init__.py
venv/Lib/site-packages/charset_normalizer/__main__.py
venv/Lib/site-packages/charset_normalizer/api.py
venv/Lib/site-packages/charset_normalizer/cd.py
venv/Lib/site-packages/charset_normalizer/constant.py
venv/Lib/site-packages/charset_normalizer/legacy.py
venv/Lib/site-packages/charset_normalizer/md.py
venv/Lib/site-packages/charset_normalizer/models.py
venv/Lib/site-packages/charset_normalizer/py.typed
venv/Lib/site-packages/charset_normalizer/utils.py
venv/Lib/site-packages/charset_normalizer/version.py
venv/Lib/site-packages/charset_normalizer/cli/__init__.py
venv/Lib/site-packages/charset_normalizer/cli/__main__.py
venv/Lib/site-packages/colorama/__init__.py
venv/Lib/site-packages/colorama/ansi.py
venv/Lib/site-packages/colorama/ansitowin32.py
venv/Lib/site-packages/colorama/initialise.py
venv/Lib/site-packages/colorama/win32.py
venv/Lib/site-packages/colorama/winterm.py
venv/Lib/site-packages/colorama/tests/__init__.py
venv/Lib/site-packages/colorama/tests/ansi_test.py
venv/Lib/site-packages/colorama/tests/ansitowin32_test.py
venv/Lib/site-packages/colorama/tests/initialise_test.py
sgupfcmed-0.0.1.dist-info/METADATA
sgupfcmed-0.0.1.dist-info/WHEEL
sgupfcmed-0.0.1.dist-info/top_level.txt
sgupfcmed-0.0.1.dist-info/RECORD
