Metadata-Version: 2.4
Name: sgUPFCMed
Version: 0.0.1
Summary: A library for String Grammar Unsupervised Possibilistic Fuzzy C-Medians
Author-email: Computational Intelligence Research Laboratory <cilabcmu@gmail.com>
License: MIT
Requires-Python: >=3.7
License-File: LICENSE
Provides-Extra: dev
Requires-Dist: pytest; extra == "dev"
Dynamic: license-file
